AUTHORS.rst
CONTRIBUTING.rst
HISTORY.rst
LICENSE
MANIFEST.in
README.rst
setup.cfg
setup.py
django_simplemenu_simplified.egg-info/PKG-INFO
django_simplemenu_simplified.egg-info/SOURCES.txt
django_simplemenu_simplified.egg-info/dependency_links.txt
django_simplemenu_simplified.egg-info/not-zip-safe
django_simplemenu_simplified.egg-info/top_level.txt
docs/Makefile
docs/authors.rst
docs/conf.py
docs/contributing.rst
docs/history.rst
docs/index.rst
docs/installation.rst
docs/make.bat
docs/readme.rst
docs/usage.rst
simplemenu/__init__.py
simplemenu/admin.py
simplemenu/models.py
simplemenu/simplemenu.py
simplemenu/urls.py
simplemenu/templatetags/__init__.py
simplemenu/templatetags/simplemenu_tags.py
tests/__init__.py
tests/test_simplemenu.py